LICENSE
MANIFEST.in
README.rst
setup.py
runipy/__init__.py
runipy/main.py
runipy/notebook_runner.py
runipy.egg-info/PKG-INFO
runipy.egg-info/SOURCES.txt
runipy.egg-info/dependency_links.txt
runipy.egg-info/entry_points.txt
runipy.egg-info/requires.txt
runipy.egg-info/top_level.txt