Metadata-Version: 1.1
Name: runipy
Version: 0.1.2
Summary: Run IPython notebooks from the command line
Home-page: https://github.com/paulgb/runipy
Author: Paul Butler
Author-email: paulgb@gmail.com
License: UNKNOWN
Platform: UNKNOWN
Classifier: Framework :: IPython
